{
  "version": "7",
  "dialect": "postgresql",
  "entries": [
    {
      "idx": 0,
      "version": "7",
      "when": 1776363618095,
      "tag": "0000_easy_karma",
      "breakpoints": true
    },
    {
      "idx": 1,
      "version": "7",
      "when": 1776364724653,
      "tag": "0001_burly_loki",
      "breakpoints": true
    },
    {
      "idx": 2,
      "version": "7",
      "when": 1776423112735,
      "tag": "0002_warm_elektra",
      "breakpoints": true
    },
    {
      "idx": 3,
      "version": "7",
      "when": 1776433989473,
      "tag": "0003_dusty_saracen",
      "breakpoints": true
    },
    {
      "idx": 4,
      "version": "7",
      "when": 1776437612846,
      "tag": "0004_bumpy_magik",
      "breakpoints": true
    },
    {
      "idx": 5,
      "version": "7",
      "when": 1776448752545,
      "tag": "0005_known_squirrel_girl",
      "breakpoints": true
    }
  ]
}